README.rst
setup.py
herokal/__init__.py
herokal/settings.py
herokal/management/__init__.py
herokal/management/commands/__init__.py
herokal/management/commands/exportenv.py
herokal_settings.egg-info/PKG-INFO
herokal_settings.egg-info/SOURCES.txt
herokal_settings.egg-info/dependency_links.txt
herokal_settings.egg-info/requires.txt
herokal_settings.egg-info/top_level.txt