Metadata-Version: 1.0
Name: herokal-settings
Version: 0.0.1
Summary: Make your django local_settings play nice with Heroku
Home-page: https://github.com/drinks/herokal-settings
Author: Dan Drinkard
Author-email: dan.drinkard@gmail.com
License: BSD
Platform: any
